hashstation/__init__.py
hashstation/core.py
hashstation/lib/__init__.py
hashstation/lib/analyze.py
hashstation-0.1.1.dist-info/METADATA
hashstation-0.1.1.dist-info/WHEEL
hashstation-0.1.1.dist-info/licenses/LICENSE
hashstation-0.1.1.dist-info/RECORD
