Metadata-Version: 2.4
Name: hashstation
Version: 0.1.1
Summary: Crack the Hash
Project-URL: Homepage, https://github.com/hadespwnme/kertash
Author-email: hades <hadespwn0@gmail.com>
License: MIT License
License-File: LICENSE
Classifier: License :: OSI Approved :: MIT License
Classifier: Operating System :: OS Independent
Classifier: Programming Language :: Python :: 3
Requires-Python: >=3.8
Requires-Dist: requests
